{"settings":{"name":"日本パデル協会 第5回全国ベテラン大会","venue":"Padel Dojo","d1":"2026-05-23","d2":"2026-05-24","courts":4},"cats":[{"id":"m35","label":"男子35+","gender":"M","age":35,"active":true},{"id":"m40","label":"男子40+","gender":"M","age":40,"active":true},{"id":"m45","label":"男子45+","gender":"M","age":45,"active":false},{"id":"m50","label":"男子50+","gender":"M","age":50,"active":true},{"id":"m55","label":"男子55+","gender":"M","age":55,"active":true},{"id":"m60","label":"男子60+","gender":"M","age":60,"active":true},{"id":"f35","label":"女子35+","gender":"F","age":35,"active":true},{"id":"f40","label":"女子40+","gender":"F","age":40,"active":false},{"id":"f45","label":"女子45+","gender":"F","age":45,"active":true},{"id":"f50","label":"女子50+","gender":"F","age":50,"active":true},{"id":"f55","label":"女子55+","gender":"F","age":55,"active":true},{"id":"f60","label":"女子60+","gender":"F","age":60,"active":false}],"draws":{"m35":{"pairs":["間彦 学武/南 和樹","","2","3","4","5","","6"],"scores":{},"winners":{"r0_m0":0,"r0_m3":1},"drawSize":8},"m40":{"pairs":["北尾 太一/鈴木 雄太","","8","9","10","11","12","13","14","15","16","17","18","19","20","平田 健一郎/大久保 祐輔"],"scores":{},"winners":{"r0_m0":0},"drawSize":16},"m45":{"pairs":[],"scores":{},"winners":{}},"m50":{"pairs":["玉井 勝善し）・西尾 健成","23","24","25","26","27","28","29"],"scores":{},"winners":{},"drawSize":8},"m55":{"pairs":["30","31","32","33"],"scores":{},"winners":{},"drawSize":4},"m60":{"pairs":["高橋 俊文/廣瀬 吉彦","長瀬 聡/南 憲生","辻本 雅一/田中 雅彦"],"scores":{},"winners":{}},"f35":{"pairs":["50","","52","53","","54","","55"],"scores":{},"winners":{"r0_m0":0,"r0_m2":1,"r0_m3":1},"drawSize":8},"f40":{"pairs":[],"scores":{},"winners":{}},"f45":{"pairs":["56","","57","58","59","60","","61"],"scores":{},"winners":{"r0_m0":0,"r0_m3":1},"drawSize":8},"f50":{"pairs":["田中 志生/谷口 桃子\t\t\t\t","","63","64","65","66","67","山本 亜紀/山下 智恵"],"scores":{},"winners":{"r0_m0":0},"drawSize":8},"f55":{"pairs":["福森 喜久子/渋谷 奈緒美","70","71","北川 美喜/山中 益子 "],"scores":{},"winners":{},"drawSize":4},"f60":{"pairs":[],"scores":{},"winners":{}}}}